[{"id":"1","nama":"Meet Up cafe","latitude":"-6.235064","longitude":"106.740530"},
{"id":"2","nama":"What's Up Cafe","latitude":"-6.211752","longitude":"106.737470"},
{"id":"3","nama":"Kafe Ten","latitude":"-6.247322","longitude":"106.745107"},
{"id":"4","nama":"Kedai Kopi Thai","latitude":"-6.236485","longitude":"106.745920"},
{"id":"5","nama":"Martabak Orins Ciledug","latitude":"-6.236491","longitude":"106.743747"}
{"id":"6","nama":"Tenda Ngemil","latitude":"-6.231444","longitude":"106.727873"}
{"id":"7","nama":"Tamarin Cafe","latitude":"-6.248135","longitude":"106.746459"}
{"id":"8","nama":"Somay Bang Yono","latitude":"-6.236214","longitude":"106.747037"}
{"id":"9","nama":"Food Updated","latitude":"-6.236203","longitude":"106.748308"}
{"id":"10","nama":"Roti Bakar 88","latitude":"-6.236700","longitude":"106.749754"}
{"id":"11","nama":"Port Steak n Fish","latitude":"-6.236243","longitude":"106.746082"}]